fcodes_fast.cpython-36m-darwin.so
emda/__init__.py
emda/config.py
emda/emda_cmd_caller.py
emda/emda_methods.py
emda/emda_test.py
emda/fouriersp_corr_3d.py
emda/fsc.py
emda/fsc_true_from_phase_randomize.py
emda/half2full.py
emda/iotools.py
emda/lowpass_map.py
emda/map_fsc.py
emda/maptools.py
emda/maskmap_class.py
emda/plotter.py
emda/quaternions.py
emda/realsp_corr_3d.py
emda/restools.py
emda/transform_map.py
emda/mapfit/__init__.py
emda/mapfit/curve_fit_3.py
emda/mapfit/derivatives_newmethod2.py
emda/mapfit/emfit_Class.py
emda/mapfit/frequency_marching.py
emda/mapfit/map_Class.py
emda/mapfit/mapaverage.py
emda/mapfit/mapoverlay.py
emda/mapfit/mapoverlay_original.py
emda/mapfit/rotmat2quart.py
emda/mapfit/utils.py
emda-1.1.2.dist-info/DESCRIPTION.rst
emda-1.1.2.dist-info/METADATA
emda-1.1.2.dist-info/RECORD
emda-1.1.2.dist-info/WHEEL
emda-1.1.2.dist-info/dependency_links.txt
emda-1.1.2.dist-info/entry_points.txt
emda-1.1.2.dist-info/metadata.json
emda-1.1.2.dist-info/top_level.txt
